cmc_dataeng_internship_laura_paz/__init__.py
cmc_dataeng_internship_laura_paz/exercise13.py
cmc_dataeng_internship_laura_paz-0.0.1.dist-info/LICENSE
cmc_dataeng_internship_laura_paz-0.0.1.dist-info/METADATA
cmc_dataeng_internship_laura_paz-0.0.1.dist-info/WHEEL
cmc_dataeng_internship_laura_paz-0.0.1.dist-info/top_level.txt
cmc_dataeng_internship_laura_paz-0.0.1.dist-info/RECORD
