Metadata-Version: 2.1
Name: cmc_dataeng_internship_laura_paz
Version: 0.0.1
Summary: Exercise 13
Home-page: UNKNOWN
Author: Laura Paz
License: UNKNOWN
Platform: UNKNOWN
Classifier: Programming Language :: Python :: 3
Classifier: License :: OSI Approved :: MIT License
Classifier: Operating System :: OS Independent
Requires-Python: >=3.6
License-File: LICENSE
